README.txt
setup.py
collective/__init__.py
collective/__init__.pyc
collective.portlet.toc.egg-info/PKG-INFO
collective.portlet.toc.egg-info/SOURCES.txt
collective.portlet.toc.egg-info/dependency_links.txt
collective.portlet.toc.egg-info/entry_points.txt
collective.portlet.toc.egg-info/namespace_packages.txt
collective.portlet.toc.egg-info/not-zip-safe
collective.portlet.toc.egg-info/requires.txt
collective.portlet.toc.egg-info/top_level.txt
collective/portlet/__init__.py
collective/portlet/__init__.pyc
collective/portlet/toc/__init__.py
collective/portlet/toc/configure.zcml
collective/portlet/toc/interfaces.py
collective/portlet/toc/tocportlet.pt
collective/portlet/toc/tocportlet.py
collective/portlet/toc/profiles/default/metadata.xml
collective/portlet/toc/profiles/default/portlets.xml
collective/portlet/toc/tests/__init__.py
collective/portlet/toc/tests/__init__.pyo
collective/portlet/toc/tests/base.py
collective/portlet/toc/tests/test_portlet.py
docs/HISTORY.txt
docs/INSTALL.txt