Metadata-Version: 1.0
Name: collective.portlet.toc
Version: 0.2
Summary: Portlet that shows the table of contents for the current item
Home-page: https://svn.v2.nl/plone/collective.portlet.toc
Author: David Jonas
Author-email: david@bv2.nl
License: GPL
Keywords: plone portlet toc table contents
Platform: UNKNOWN
Classifier: Framework :: Plone
Classifier: Programming Language :: Python
